CVineModel/CvineCopulaModel.py
CVineModel-0.0.3.dist-info/DESCRIPTION.rst
CVineModel-0.0.3.dist-info/METADATA
CVineModel-0.0.3.dist-info/RECORD
CVineModel-0.0.3.dist-info/WHEEL
CVineModel-0.0.3.dist-info/metadata.json
CVineModel-0.0.3.dist-info/top_level.txt
