Metadata-Version: 2.0
Name: CVineModel
Version: 0.0.3
Summary: CVine Colpula Model
Home-page: UNKNOWN
Author: Yili Peng
Author-email: yili_peng@outlook.com
License: UNKNOWN
Keywords: Vine Copula
Platform: UNKNOWN
